npbcharger/__init__.py
npbcharger/commands.py
npbcharger/driver.py
npbcharger/exceptions.py
npbcharger/services.py
npbcharger/internal/utils/direct_canusb.py
npbcharger/parsers/__init__.py
npbcharger/parsers/base.py
npbcharger/parsers/bytes_forward.py
npbcharger/parsers/charge_status.py
npbcharger/parsers/curve_config.py
npbcharger/parsers/electric_data.py
npbcharger/parsers/fault_status.py
npbcharger/parsers/system_config.py
npbcharger/parsers/system_status.py
npbcharger/parsers/factories/__init__.py
npbcharger/parsers/factories/base_factory.py
npbcharger/parsers/factories/config_factory.py
npbcharger/parsers/factories/status_factory.py
npbcharger-1.1.0.dist-info/licenses/LICENSE
npbcharger-1.1.0.dist-info/METADATA
npbcharger-1.1.0.dist-info/WHEEL
npbcharger-1.1.0.dist-info/top_level.txt
npbcharger-1.1.0.dist-info/RECORD
