Metadata-Version: 2.4
Name: npbcharger
Version: 1.1.0
Summary: A driver and service layer for the Mean Well NPB-1700 CAN bus charger.
Author-email: Ilia Kliantsevich <iliawork112005@gmail.com>
Requires-Python: >=3.8
License-File: LICENSE
Requires-Dist: pyserial
Requires-Dist: python-can
Dynamic: license-file
